src/__init__.py
src/convert.py
src/expand_value_set.py
src/fhirgenconvert.py
fhirgenconvert-0.0.3.dist-info/METADATA
fhirgenconvert-0.0.3.dist-info/WHEEL
fhirgenconvert-0.0.3.dist-info/entry_points.txt
fhirgenconvert-0.0.3.dist-info/top_level.txt
fhirgenconvert-0.0.3.dist-info/RECORD
