Metadata-Version: 2.1
Name: fhirgenconvert
Version: 0.0.3
Summary: A companion package for FHIR Generator to convert struture definitions to class wrappers.
Home-page: https://github.com/SmartChartSuite/FHIRGenConvert
Author: Elizabeth Shivers
Author-email: elizabeth.shivers@gtri.gatech.edu
Project-URL: Bug Tracker, https://github.com/SmartChartSuite/FHIRGenConvert/issues
Classifier: Programming Language :: Python :: 3.10
Classifier: License :: OSI Approved :: MIT License
Classifier: Operating System :: OS Independent
Requires-Python: >=3.10
